AUTHORS
CHANGELOG.txt
DESCRIPTION
LICENSE
MANIFEST.in
setup.py
cmsplugin_redirect/__init__.py
cmsplugin_redirect/admin.py
cmsplugin_redirect/cms_plugins.py
cmsplugin_redirect/middleware.py
cmsplugin_redirect/models.py
cmsplugin_redirect.egg-info/PKG-INFO
cmsplugin_redirect.egg-info/SOURCES.txt
cmsplugin_redirect.egg-info/dependency_links.txt
cmsplugin_redirect.egg-info/requires.txt
cmsplugin_redirect.egg-info/top_level.txt
cmsplugin_redirect/migrations/0001_initial.py
cmsplugin_redirect/migrations/__init__.py
cmsplugin_redirect/templates/base.html
cmsplugin_redirect/templates/standard.html
cmsplugin_redirect/tests/__init__.py
cmsplugin_redirect/tests/cms_plugins_tests.py
cmsplugin_redirect/tests/cmsplugin_tests.py
cmsplugin_redirect/tests/factories.py
cmsplugin_redirect/tests/models_tests.py
cmsplugin_redirect/tests/runtests.py
cmsplugin_redirect/tests/south_settings.py
cmsplugin_redirect/tests/test_settings.py
cmsplugin_redirect/tests/urls.py