Metadata-Version: 1.0
Name: cmsplugin-redirect
Version: 0.2.1
Summary: A reusable Django app to add custom redirect actions to Django-CMS.
